<?xml version="1.0" encoding="utf-8" ?>
<dwsync>
<file name="Year.cfc" server="H:/wwwroot/mochi/" local="128756666692500000" remote="128756666690000000" Dst="-1" />
<file name="YearDAO.cfc" server="H:/wwwroot/mochi/" local="128756665489687500" remote="128756665480000000" Dst="-1" />
<file name="YearGateway.cfc" server="H:/wwwroot/mochi/" local="128756665492187500" remote="128756665490000000" Dst="-1" />
<file name="Year.cfc" server="M:/wwwroot/mochi/" local="128756666692500000" remote="128756666690000000" Dst="-1" />
<file name="YearDAO.cfc" server="M:/wwwroot/mochi/" local="128756665489687500" remote="128756665480000000" Dst="-1" />
<file name="YearGateway.cfc" server="M:/wwwroot/mochi/" local="128756665492187500" remote="128756665490000000" Dst="-1" />
<file name="YearGateway.cfc" server="N:/wwwroot/mochi/" local="128756665492187500" remote="128756665490000000" Dst="-1" />
<file name="Year.cfc" server="V:/wwwroot/mochi/" local="130338497637153790" remote="130338497630000000" Dst="1" />
<file name="YearDAO.cfc" server="V:/wwwroot/mochi/" local="130338497637163790" remote="130338497630000000" Dst="1" />
<file name="YearGateway.cfc" server="V:/wwwroot/mochi/" local="130338497637173790" remote="130338497630000000" Dst="1" />
</dwsync>